ezdnsbl/__init__.py
ezdnsbl/classes.py
ezdnsbl/query.py
ezdnsbl/utils.py
ezdnsbl/version.py
ezdnsbl/provider/__init__.py
ezdnsbl/provider/apews.py
ezdnsbl/provider/cymru.py
ezdnsbl/provider/dan.py
ezdnsbl/provider/dnsbl.py
ezdnsbl/provider/gbudb.py
ezdnsbl/provider/honeypot.py
ezdnsbl/provider/httpbl_apikey.py
ezdnsbl/provider/httpbl_apikey.py.sample
ezdnsbl/provider/lashback.py
ezdnsbl/provider/spamhaus.py
ezdnsbl/provider/surriel.py
ezdnsbl-0.2.1.dist-info/LICENSE.txt
ezdnsbl-0.2.1.dist-info/METADATA
ezdnsbl-0.2.1.dist-info/WHEEL
ezdnsbl-0.2.1.dist-info/entry_points.txt
ezdnsbl-0.2.1.dist-info/top_level.txt
ezdnsbl-0.2.1.dist-info/RECORD
