Metadata-Version: 2.1
Name: ezdnsbl
Version: 0.2.1
Summary: Easy DNSBL querying
Home-page: https://bitbucket.org/c0nch0b4r/ezdnsbl/
Author: c0nch0b4r
Author-email: lp1.on.fire@gmail.com
License: UNKNOWN
Download-URL: https://bitbucket.org/c0nch0b4r/ezdnsbl/get/0.2.1.tar.gz
Project-URL: Source, https://bitbucket.org/c0nch0b4r/ezdnsbl/
Keywords: dnsbl blacklist dns
Platform: UNKNOWN
Classifier: Development Status :: 5 - Production/Stable
Classifier: Environment :: Console
Classifier: Intended Audience :: Information Technology
Classifier: License :: OSI Approved :: GNU General Public License v3 or later (GPLv3+)
Classifier: Natural Language :: English
Classifier: Operating System :: OS Independent
Classifier: Programming Language :: Python :: 2.7
Classifier: Topic :: Internet
Classifier: Topic :: Security
Requires-Python: ~=2.7
Requires-Dist: dnspython
